nonebot_plugin_xiuxian_2/__init__.py
nonebot_plugin_xiuxian_2/xiuxian/__init__.py
nonebot_plugin_xiuxian_2/xiuxian/config.py
nonebot_plugin_xiuxian_2/xiuxian/data_source.py
nonebot_plugin_xiuxian_2/xiuxian/download_xiuxian_data.py
nonebot_plugin_xiuxian_2/xiuxian/item_json.py
nonebot_plugin_xiuxian_2/xiuxian/lay_out.py
nonebot_plugin_xiuxian_2/xiuxian/player_fight.py
nonebot_plugin_xiuxian_2/xiuxian/read_buff.py
nonebot_plugin_xiuxian_2/xiuxian/utils.py
nonebot_plugin_xiuxian_2/xiuxian/xiuxian2_handle.py
nonebot_plugin_xiuxian_2/xiuxian/xiuxian_config.py
nonebot_plugin_xiuxian_2/xiuxian/xiuxian_opertion.py
nonebot_plugin_xiuxian_2/xiuxian/xn_xiuxian_impart.py
nonebot_plugin_xiuxian_2/xiuxian/xn_xiuxian_impart_config.py
nonebot_plugin_xiuxian_2/xiuxian/xiuxian_back/__init__.py
nonebot_plugin_xiuxian_2/xiuxian/xiuxian_back/back_util.py
nonebot_plugin_xiuxian_2/xiuxian/xiuxian_back/backconfig.py
nonebot_plugin_xiuxian_2/xiuxian/xiuxian_back/xiuxian_back/__init__.py
nonebot_plugin_xiuxian_2/xiuxian/xiuxian_back/xiuxian_back/back_util.py
nonebot_plugin_xiuxian_2/xiuxian/xiuxian_bank/__init__.py
nonebot_plugin_xiuxian_2/xiuxian/xiuxian_bank/bankconfig.py
nonebot_plugin_xiuxian_2/xiuxian/xiuxian_base/__init__.py
nonebot_plugin_xiuxian_2/xiuxian/xiuxian_boss/__init__.py
nonebot_plugin_xiuxian_2/xiuxian/xiuxian_boss/bossconfig.py
nonebot_plugin_xiuxian_2/xiuxian/xiuxian_boss/makeboss.py
nonebot_plugin_xiuxian_2/xiuxian/xiuxian_boss/old_boss_info.py
nonebot_plugin_xiuxian_2/xiuxian/xiuxian_buff/__init__.py
nonebot_plugin_xiuxian_2/xiuxian/xiuxian_buff/two_exp_cd.py
nonebot_plugin_xiuxian_2/xiuxian/xiuxian_impart/__init__.py
nonebot_plugin_xiuxian_2/xiuxian/xiuxian_impart/impart_all.py
nonebot_plugin_xiuxian_2/xiuxian/xiuxian_impart/impart_data.py
nonebot_plugin_xiuxian_2/xiuxian/xiuxian_impart/impart_uitls.py
nonebot_plugin_xiuxian_2/xiuxian/xiuxian_impart_pk/__init__.py
nonebot_plugin_xiuxian_2/xiuxian/xiuxian_impart_pk/impart_pk.py
nonebot_plugin_xiuxian_2-2.9.2.2.dist-info/METADATA
nonebot_plugin_xiuxian_2-2.9.2.2.dist-info/WHEEL
nonebot_plugin_xiuxian_2-2.9.2.2.dist-info/top_level.txt
nonebot_plugin_xiuxian_2-2.9.2.2.dist-info/RECORD
