Metadata-Version: 2.1
Name: nonebot-plugin-xiuxian-2
Version: 2.9.2.2
Summary: 修仙插件
Home-page: https://github.com/QingMuCat/nonebot_plugin_xiuxian_2
Author: QingmuCat
Author-email: 1242550160@qq.com
Keywords: pip,nonebot2,文游,修仙
Platform: any
Classifier: Programming Language :: Python :: 3
Classifier: License :: OSI Approved :: GNU General Public License v3 (GPLv3)
Classifier: Natural Language :: Chinese (Simplified)
Requires-Dist: fastapi (==0.89.1)
Requires-Dist: nonebot-adapter-onebot (==2.2.1)
Requires-Dist: nonebot-plugin-apscheduler (==0.2.0)
Requires-Dist: nonebot2 (==2.0.0rc3)
Requires-Dist: numpy (==1.23.5)
Requires-Dist: Pillow (==9.4.0)
Requires-Dist: urllib3 (==1.26.14)
Requires-Dist: ujson (==5.7.0)
Requires-Dist: uvicorn (==0.20.0)
Requires-Dist: wcwidth (==0.2.6)
Requires-Dist: websockets (==10.4)
Requires-Dist: wget (==3.2)
Requires-Dist: aiohttp (==3.8.4)
